djangologinapp
