Metadata-Version: 1.1
Name: djangologinapp
Version: 0.1.2
Summary: A simple Django app to login and also with mongoengine as User backend.
Home-page: https://github.com/abdullatheef/djangologinapp
Author: latheef
Author-email: latheefvkpadi@gmail.com
License: BSD License
Platform: UNKNOWN
Classifier: Environment :: Web Environment
Classifier: Framework :: Django
Classifier: Intended Audience :: Developers
